roamnerd_private_cli.py
roamnerd_private_cli-0.1.1.dist-info/entry_points.txt
roamnerd_private_cli-0.1.1.dist-info/WHEEL
roamnerd_private_cli-0.1.1.dist-info/METADATA
roamnerd_private_cli-0.1.1.dist-info/RECORD
