Metadata-Version: 2.1
Name: roamnerd-private-cli
Version: 0.1.1
Summary: A private CLI for roamNERd developers / power users. Runs all NER locally using spacy
License: Proprietary
Author: hmprt
Author-email: hmprt@protonmail.com
Requires-Python: >=3.5,<4.0
Classifier: License :: Other/Proprietary License
Classifier: Programming Language :: Python :: 3
Classifier: Programming Language :: Python :: 3.5
Classifier: Programming Language :: Python :: 3.6
Classifier: Programming Language :: Python :: 3.7
Classifier: Programming Language :: Python :: 3.8
Requires-Dist: argh (>=0.26.2,<0.27.0)
Requires-Dist: python-dateutil (>=2.8.1,<3.0.0)
Requires-Dist: spacy (>=2.3.2,<3.0.0)
